scATAnno/SnapATAC2_spectral.py
scATAnno/SnapATAC2_tools.py
scATAnno/SnapATAC2_utils.py
scATAnno/__init__.py
scATAnno/scATAnno_assignment.py
scATAnno/scATAnno_evaluation.py
scATAnno/scATAnno_integration.py
scATAnno/scATAnno_plotting.py
scATAnno/scATAnno_preprocess.py
scATAnno-1.0.2.dist-info/METADATA
scATAnno-1.0.2.dist-info/WHEEL
scATAnno-1.0.2.dist-info/top_level.txt
scATAnno-1.0.2.dist-info/RECORD
