Metadata-Version: 2.1
Name: scATAnno
Version: 1.0.2
Home-page: https://github.com/aj088/scATAnno-main/
Author: Yijia Jiang
Author-email: yijia_jiang@dfci.harvard.edu
Requires-Dist: pandas
Requires-Dist: scanpy
Requires-Dist: anndata
Requires-Dist: matplotlib
Requires-Dist: adjustText
Requires-Dist: leidenalg
Requires-Dist: harmonypy
Requires-Dist: scipy
Requires-Dist: seaborn
Requires-Dist: snapatac2
